hvplot/__init__.py
hvplot/_version.py
hvplot/backend_transforms.py
hvplot/converter.py
hvplot/cudf.py
hvplot/dask.py
hvplot/datasets.yaml
hvplot/duckdb.py
hvplot/fugue.py
hvplot/ibis.py
hvplot/intake.py
hvplot/interactive.py
hvplot/networkx.py
hvplot/pandas.py
hvplot/polars.py
hvplot/sample_data.py
hvplot/sampledata.py
hvplot/streamz.py
hvplot/ui.py
hvplot/util.py
hvplot/utilities.py
hvplot/xarray.py
hvplot/data/crime.csv
hvplot/plotting/__init__.py
hvplot/plotting/andrews_curves.py
hvplot/plotting/core.py
hvplot/plotting/lag_plot.py
hvplot/plotting/parallel_coordinates.py
hvplot/plotting/scatter_matrix.py
hvplot/tests/__init__.py
hvplot/tests/conftest.py
hvplot/tests/test_links.py
hvplot/tests/testbackend_transforms.py
hvplot/tests/testcharts.py
hvplot/tests/testdeprecations.py
hvplot/tests/testdocstring.py
hvplot/tests/testfugue.py
hvplot/tests/testgeo.py
hvplot/tests/testgeowithoutgv.py
hvplot/tests/testgridplots.py
hvplot/tests/testhelp.py
hvplot/tests/testibis.py
hvplot/tests/testinteractive.py
hvplot/tests/testnetworkx.py
hvplot/tests/testoperations.py
hvplot/tests/testoptions.py
hvplot/tests/testoverrides.py
hvplot/tests/testpanel.py
hvplot/tests/testpatch.py
hvplot/tests/testpatchsignature.py
hvplot/tests/testplotting.py
hvplot/tests/teststatplots.py
hvplot/tests/teststreaming.py
hvplot/tests/testtransforms.py
hvplot/tests/testui.py
hvplot/tests/testutil.py
hvplot/tests/util.py
hvplot/tests/data/README.md
hvplot/tests/data/RGB-red.byte.tif
hvplot/tests/plotting/__init__.py
hvplot/tests/plotting/testandrewscurves.py
hvplot/tests/plotting/testcore.py
hvplot/tests/plotting/testohlc.py
hvplot/tests/plotting/testscattermatrix.py
hvplot-0.12.1.dist-info/METADATA
hvplot-0.12.1.dist-info/WHEEL
hvplot-0.12.1.dist-info/entry_points.txt
hvplot-0.12.1.dist-info/licenses/LICENSE
hvplot-0.12.1.dist-info/RECORD
